pure_lambda_ric/__init__.py
pure_lambda_ric/_init.py
pure_lambda_ric/_listener.py
pure_lambda_ric/_main.py
pure_lambda_ric/_utils.py
pure_lambda_ric/py.typed
pure_lambda_ric/_api/__init__.py
pure_lambda_ric/_api/_client.py
pure_lambda_ric/_api/core.py
pure_lambda_ric-1.0.1.dist-info/WHEEL
pure_lambda_ric-1.0.1.dist-info/METADATA
pure_lambda_ric-1.0.1.dist-info/RECORD
