Metadata-Version: 2.4
Name: pure_lambda_ric
Version: 1.0.1
Summary: Full typed implementation of the aws lambda runtime API
Author-email: Product Team <development@fluidattacks.com>
Requires-Python: >=3.11
Requires-Dist: fa-purity >=2.5.2, <3.0.0
Requires-Dist: pure-requests >=3.0.0, <4.0.0
